thonnycontrib/backend/__init__.py
thonnycontrib/backend/emac_backend.py
thonnycontrib/backend/api_stubs/_thread.py
thonnycontrib/backend/api_stubs/array.py
thonnycontrib/backend/api_stubs/binascii.py
thonnycontrib/backend/api_stubs/builtins.py
thonnycontrib/backend/api_stubs/cmath.py
thonnycontrib/backend/api_stubs/collections.py
thonnycontrib/backend/api_stubs/dht.py
thonnycontrib/backend/api_stubs/errno.py
thonnycontrib/backend/api_stubs/framebuf.py
thonnycontrib/backend/api_stubs/gc.py
thonnycontrib/backend/api_stubs/hashlib.py
thonnycontrib/backend/api_stubs/heapq.py
thonnycontrib/backend/api_stubs/io.py
thonnycontrib/backend/api_stubs/json.py
thonnycontrib/backend/api_stubs/lcd160cr.py
thonnycontrib/backend/api_stubs/lcd160cr_test.py
thonnycontrib/backend/api_stubs/logging.py
thonnycontrib/backend/api_stubs/machine.py
thonnycontrib/backend/api_stubs/math.py
thonnycontrib/backend/api_stubs/micropython.py
thonnycontrib/backend/api_stubs/network.py
thonnycontrib/backend/api_stubs/onewire.py
thonnycontrib/backend/api_stubs/os.py
thonnycontrib/backend/api_stubs/pyb.py
thonnycontrib/backend/api_stubs/random.py
thonnycontrib/backend/api_stubs/re.py
thonnycontrib/backend/api_stubs/select.py
thonnycontrib/backend/api_stubs/socket.py
thonnycontrib/backend/api_stubs/stm.py
thonnycontrib/backend/api_stubs/struct.py
thonnycontrib/backend/api_stubs/sys.py
thonnycontrib/backend/api_stubs/time.py
thonnycontrib/backend/api_stubs/uarray.py
thonnycontrib/backend/api_stubs/ubinascii.py
thonnycontrib/backend/api_stubs/ucollections.py
thonnycontrib/backend/api_stubs/uctypes.py
thonnycontrib/backend/api_stubs/uerrno.py
thonnycontrib/backend/api_stubs/uhashlib.py
thonnycontrib/backend/api_stubs/uheapq.py
thonnycontrib/backend/api_stubs/uio.py
thonnycontrib/backend/api_stubs/ujson.py
thonnycontrib/backend/api_stubs/umachine.py
thonnycontrib/backend/api_stubs/uos.py
thonnycontrib/backend/api_stubs/urandom.py
thonnycontrib/backend/api_stubs/ure.py
thonny_emac-0.1.0.dist-info/LICENSE.txt
thonny_emac-0.1.0.dist-info/METADATA
thonny_emac-0.1.0.dist-info/WHEEL
thonny_emac-0.1.0.dist-info/top_level.txt
thonny_emac-0.1.0.dist-info/RECORD
